django_simplethumb-0.3.1.dist-info/METADATA
django_simplethumb-0.3.1.dist-info/RECORD
django_simplethumb-0.3.1.dist-info/WHEEL
django_simplethumb-0.3.1.dist-info/top_level.txt
simplethumb/__init__.py
simplethumb/conf.py
simplethumb/models.py
simplethumb/spec.py
simplethumb/urls.py
simplethumb/views.py
simplethumb/templatetags/__init__.py
simplethumb/templatetags/simplethumb_tags.py
tests/__init__.py
tests/settings.py
tests/test_image_proc.py
tests/test_littlefloat.py
tests/test_spec.py
tests/test_templatetag.py
tests/test_view.py
