Metadata-Version: 2.1
Name: django-simplethumb
Version: 0.3.1
Summary: Django template tag to do some basic image processing, and cache the resulting image
Home-page: http://github.com/jscaltreto/django-simplethumb
Author: Jake Scaltreto
Author-email: jscaltreto@gmail.com
License: BSD
Platform: UNKNOWN
Classifier: Environment :: Web Environment
Classifier: Intended Audience :: Developers
Classifier: License :: OSI Approved :: BSD License
Classifier: Operating System :: OS Independent
Classifier: Programming Language :: Python
Classifier: Programming Language :: Python :: 2.7
Classifier: Programming Language :: Python :: 3.4
Classifier: Programming Language :: Python :: 3.5
Classifier: Programming Language :: Python :: 3.6
Classifier: Topic :: Utilities
Classifier: Framework :: Django
Requires-Dist: django
Requires-Dist: six
Requires-Dist: django-appconf
Requires-Dist: Pillow
